weightsplitter/__init__.py
weightsplitter/errors.py
weightsplitter/main.py
weightsplitter/server_test.py
weightsplitter/settings.py
weightsplitter/support_functions.py
weightsplitter/terminals/__init__.py
weightsplitter/terminals/A12E/__init__.py
weightsplitter/terminals/A12E/functions.py
weightsplitter/terminals/CAS/__init__.py
weightsplitter/terminals/CAS/functions.py
weightsplitter/terminals/CAS CL-200A/__init__.py
weightsplitter/terminals/CAS CL-200A/functions.py
weightsplitter/terminals/CAS_CL-200A/__init__.py
weightsplitter/terminals/CAS_CL-200A/functions.py
weightsplitter/terminals/None/__init__.py
weightsplitter/terminals/None/functions.py
weightsplitter/tests/__init__.py
weightsplitter/tests/client_test.py
weightsplitter/tests/main_test.py
weightsplitter/tests/settings_test.py
weightsplitter/tests/support_functions_tests.py
weightsplitter-1.20.dist-info/LICENSE
weightsplitter-1.20.dist-info/METADATA
weightsplitter-1.20.dist-info/WHEEL
weightsplitter-1.20.dist-info/top_level.txt
weightsplitter-1.20.dist-info/RECORD
